mcp_tools/__init__.py
mcp_tools/dp_tools.py
mcp_tools/main.py
tools/__init__.py
tools/browser_manager.py
tools/browser_proxy.py
tools/tools.py
jarvis_brain-0.1.11.5.dist-info/METADATA
jarvis_brain-0.1.11.5.dist-info/WHEEL
jarvis_brain-0.1.11.5.dist-info/entry_points.txt
jarvis_brain-0.1.11.5.dist-info/RECORD
