Metadata-Version: 2.4
Name: Jarvis_Brain
Version: 0.1.11.5
Summary: Jarvis brain mcp
Requires-Python: >=3.10
Requires-Dist: beautifulsoup4
Requires-Dist: curl-cffi
Requires-Dist: drissionpage
Requires-Dist: fastmcp
Requires-Dist: minify-html
Requires-Dist: pillow
